README.txt
setup.cfg
setup.py
osensanugrid/__init__.py
osensanugrid/osensanugrid.py
osensanugrid.egg-info/PKG-INFO
osensanugrid.egg-info/SOURCES.txt
osensanugrid.egg-info/dependency_links.txt
osensanugrid.egg-info/requires.txt
osensanugrid.egg-info/top_level.txt