Metadata-Version: 1.2
Name: osensanugrid
Version: 0.0.1
Summary: OSENSA-Nugrid Python library
Home-page: UNKNOWN
Author: OSENSA Innovations
Author-email: sbalaji@osensa.com
License: MIT
Platform: UNKNOWN
Requires-Python: >=2.6
